odoo/addons/ssi_product/README.rst
odoo/addons/ssi_product/__init__.py
odoo/addons/ssi_product/__manifest__.py
odoo/addons/ssi_product/menu.xml
odoo/addons/ssi_product/models/__init__.py
odoo/addons/ssi_product/models/mixin_product_category_m2o_configurator.py
odoo/addons/ssi_product/models/mixin_product_pricelist_m2o_configurator.py
odoo/addons/ssi_product/models/mixin_product_product_m2o_configurator.py
odoo/addons/ssi_product/models/mixin_product_template_m2o_configurator.py
odoo/addons/ssi_product/models/product_brand.py
odoo/addons/ssi_product/models/product_category.py
odoo/addons/ssi_product/models/product_pricelist.py
odoo/addons/ssi_product/models/product_product.py
odoo/addons/ssi_product/models/product_template.py
odoo/addons/ssi_product/security/ir.model.access.csv
odoo/addons/ssi_product/security/ir_module_category_data.xml
odoo/addons/ssi_product/security/res_group_data.xml
odoo/addons/ssi_product/static/description/icon.png
odoo/addons/ssi_product/templates/product_category_m2_configurator_templates.xml
odoo/addons/ssi_product/templates/product_pricelist_m2_configurator_templates.xml
odoo/addons/ssi_product/templates/product_product_m2_configurator_templates.xml
odoo/addons/ssi_product/templates/product_template_m2_configurator_templates.xml
odoo/addons/ssi_product/views/product_attribute_views.xml
odoo/addons/ssi_product/views/product_brand_views.xml
odoo/addons/ssi_product/views/product_category_views.xml
odoo/addons/ssi_product/views/product_packaging_views.xml
odoo/addons/ssi_product/views/product_pricelist_views.xml
odoo/addons/ssi_product/views/product_product_views.xml
odoo/addons/ssi_product/views/product_supplierinfo_views.xml
odoo/addons/ssi_product/views/product_template_views.xml
odoo/addons/ssi_product/views/uom_category_views.xml
odoo/addons/ssi_product/views/uom_uom_views.xml
odoo14_addon_ssi_product-14.0.1.13.0.dist-info/METADATA
odoo14_addon_ssi_product-14.0.1.13.0.dist-info/WHEEL
odoo14_addon_ssi_product-14.0.1.13.0.dist-info/top_level.txt
odoo14_addon_ssi_product-14.0.1.13.0.dist-info/RECORD
